flaskdoc/__init__.py
flaskdoc/cli.py
flaskdoc/core.py
flaskdoc/jo.py
flaskdoc/examples/__init__.py
flaskdoc/examples/api_with_examples.py
flaskdoc/examples/app.py
flaskdoc/examples/inventory.py
flaskdoc/examples/mocks.py
flaskdoc/examples/petstore.py
flaskdoc/examples/petstore_specs.py
flaskdoc/examples/link_example/__init__.py
flaskdoc/examples/link_example/schemas.py
flaskdoc/examples/link_example/specs.py
flaskdoc/examples/link_example/v0.py
flaskdoc/pallets/__init__.py
flaskdoc/pallets/app.py
flaskdoc/pallets/blueprints.py
flaskdoc/pallets/mixin.py
flaskdoc/pallets/plugins.py
flaskdoc/static/favicon-16x16.png
flaskdoc/static/favicon-32x32.png
flaskdoc/static/swagger-ui-bundle.js
flaskdoc/static/swagger-ui-bundle.js.map
flaskdoc/static/swagger-ui-es-bundle-core.js
flaskdoc/static/swagger-ui-es-bundle-core.js.map
flaskdoc/static/swagger-ui-es-bundle.js
flaskdoc/static/swagger-ui-es-bundle.js.map
flaskdoc/static/swagger-ui-standalone-preset.js
flaskdoc/static/swagger-ui-standalone-preset.js.map
flaskdoc/static/swagger-ui.css
flaskdoc/static/swagger-ui.css.map
flaskdoc/static/swagger-ui.js
flaskdoc/static/swagger-ui.js.map
flaskdoc/swagger/__init__.py
flaskdoc/swagger/models.py
flaskdoc/swagger/schema.py
flaskdoc/swagger/validators.py
flaskdoc/templates/index.html
flaskdoc/templates/oauth2-redirect.html
flaskdoc/templates/redoc.html
flaskdoc-0.2.0.dist-info/LICENSE
flaskdoc-0.2.0.dist-info/METADATA
flaskdoc-0.2.0.dist-info/WHEEL
flaskdoc-0.2.0.dist-info/entry_points.txt
flaskdoc-0.2.0.dist-info/top_level.txt
flaskdoc-0.2.0.dist-info/zip-safe
flaskdoc-0.2.0.dist-info/RECORD
