Metadata-Version: 2.1
Name: flaskdoc
Version: 0.2.0
Summary: Flask wrapper for programmatically composing openapi specifications
Home-page: https://github.com/kulgan/flaskdoc
Author: Rowland Ogwara
Author-email: r.ogwara@gmail.com
Maintainer: Rowland Ogwara
License: Apache 2.0
Project-URL: source, https://github.com/kulgan/flaskdoc
Keywords: swagger,openapi,flask,rest,api,swagger-ui
Platform: UNKNOWN
Classifier: Development Status :: 3 - Alpha
Classifier: Framework :: Flask
Classifier: Intended Audience :: Developers
Classifier: License :: OSI Approved :: Apache Software License
Classifier: Programming Language :: Python :: 3.6
Classifier: Programming Language :: Python :: 3.7
Classifier: Programming Language :: Python :: 3.8
Classifier: Programming Language :: Python :: 3.9
Classifier: Topic :: Documentation
Requires-Python: >=3.6
License-File: LICENSE
Requires-Dist: attrs (>=19.3)
Requires-Dist: click (>=7.1)
Requires-Dist: flask (>=0.10)
Requires-Dist: PyYaml (>=5.1)
Provides-Extra: dev
Requires-Dist: black ; extra == 'dev'
Requires-Dist: click ; extra == 'dev'
Requires-Dist: coverage[toml] ; extra == 'dev'
Requires-Dist: flake8 ; extra == 'dev'
Requires-Dist: openapi-spec-validator ; extra == 'dev'
Requires-Dist: pre-commit ; extra == 'dev'
Requires-Dist: pytest ; extra == 'dev'
Requires-Dist: pytest-cov ; extra == 'dev'
Requires-Dist: pytest-flask ; extra == 'dev'
Requires-Dist: sphinx ; extra == 'dev'
Requires-Dist: sphinx-rtd-theme ; extra == 'dev'
Requires-Dist: sphinxcontrib-napoleon ; extra == 'dev'
Provides-Extra: rtd
Requires-Dist: sphinx ; extra == 'rtd'
Requires-Dist: sphinxcontrib-napoleon ; extra == 'rtd'
